__init__.py
parent_processor.py
picture_processor.py
table_processor.py
template_pptx_options.py
templatepptx.py
text_processor.py
templatepptx-0.0.84.dist-info/licenses/LICENCE
templatepptx-0.0.84.dist-info/METADATA
templatepptx-0.0.84.dist-info/WHEEL
templatepptx-0.0.84.dist-info/top_level.txt
templatepptx-0.0.84.dist-info/RECORD
