Metadata-Version: 2.4
Name: templatepptx
Version: 0.0.84
Summary: Use template PowerPoint files to generate new PowerPoint files bases on dictionary values and magic words. Dynamically generate tables, replace text and pictures.
Author-email: Samir Sellars <samir.sellars@gmail.com>
Project-URL: Homepage, https://github.com/Samir-Sell/templatepptx
Keywords: powerpoint,pptx,template,templatepptx
Classifier: License :: OSI Approved :: MIT License
Classifier: Programming Language :: Python
Classifier: Programming Language :: Python :: 3
Requires-Python: >=3.7.10
License-File: LICENCE
Requires-Dist: lxml>=3.1.0
Requires-Dist: Pillow>=3.3.2
Requires-Dist: XlsxWriter>=0.5.7
Requires-Dist: python-pptx>=0.6.21
Dynamic: license-file
